{"1": {"category_type": [["stp - m4mw", 561]], "cities": [["dallas", 0.0018887925219234847], ["oklahomacity", 0.0017809439002671415], ["denver", 0.0014216195527366176], ["miami", 0.0014002962165073382], ["lasvegas", 0.0013376852694098132], ["washingtondc", 0.0011425368629818056], ["newyork", 0.0011075423634954037], ["chicago", 0.0010787122872071464]], "terms": ["420", "help", "coupl", "male", "work", "area", "well", "email", "enjoy", "free", "feel", "year", "meet", "peopl", "hope", "hey", "find", "interest", "fun", "time"], "categories": [["stp", 561]], "types": [["m4mw", 0.34207317073170734]]}, "3": {"category_type": [["stp - m4mw", 344]], "cities": [["sfbay", 0.0011723520312627209], ["jacksonville", 0.0011138338159946536], ["denver", 0.00087484280168407234], ["losangeles", 0.00085326658892459972], ["dallas", 0.00077093572323407532], ["lasvegas", 0.00074910375086949547], ["chicago", 0.00067419517950446657], ["seattle", 0.00065506269885831929]], "terms": ["friend", "interest", "meet", "peopl", "play", "area", "year", "hang", "male", "work", "hey", "hope", "free", "feel", "enjoy", "420", "find", "talk", "email", "time"], "categories": [["stp", 344]], "types": [["m4mw", 0.2097560975609756]]}, "2": {"category_type": [["stp - m4mw", 288]], "cities": [["lasvegas", 0.0013911926801862058], ["providence", 0.0013581923694283246], ["minneapolis", 0.00092295521469696305], ["denver", 0.00090218163923669965], ["oklahomacity", 0.00089047195013357077], ["losangeles", 0.00085326658892459972], ["dallas", 0.00069384215091066782], ["chicago", 0.00057306590257879652]], "terms": ["love", "time", "talk", "fun", "hang", "peopl", "thing", "friend", "play", "coupl", "year", "find", "work", "male", "meet", "hey", "interest", "free", "enjoy", "help"], "categories": [["stp", 288]], "types": [["m4mw", 0.17560975609756097]]}}